mahdienc/__init__.py
mahdienc-0.2.dist-info/METADATA
mahdienc-0.2.dist-info/WHEEL
mahdienc-0.2.dist-info/top_level.txt
mahdienc-0.2.dist-info/RECORD
