Metadata-Version: 2.1
Name: mahdienc
Version: 0.2
Summary: this is a simple pip modul and test
